saaya/__init__.py
saaya/config.py
saaya/event.py
saaya/logger.py
saaya/member.py
saaya/message.py
saaya/permission.py
saaya/protocol.py
saaya/session.py
saaya/utils.py
saaya-2.0.5.dist-info/LICENSE
saaya-2.0.5.dist-info/METADATA
saaya-2.0.5.dist-info/WHEEL
saaya-2.0.5.dist-info/top_level.txt
saaya-2.0.5.dist-info/RECORD
