Metadata-Version: 2.1
Name: saaya
Version: 2.0.5
Summary: Saaya is a Python framework based on Mirai
Home-page: https://github.com/jerrita/saaya
Author: Jerrita
Author-email: je5r1ta@icloud.com
License: UNKNOWN
Platform: UNKNOWN
Classifier: Programming Language :: Python :: 3
Classifier: Operating System :: OS Independent
License-File: LICENSE
Requires-Dist: requests
Requires-Dist: colorlog
Requires-Dist: websockets
